sparkle/__init__.py
sparkle/about.py
sparkle/CLI/__init__.py
sparkle/CLI/_cli_.py
sparkle/CLI/about.py
sparkle/CLI/add_feature_extractor.py
sparkle/CLI/add_instances.py
sparkle/CLI/add_solver.py
sparkle/CLI/cleanup.py
sparkle/CLI/compute_features.py
sparkle/CLI/compute_marginal_contribution.py
sparkle/CLI/configure_solver.py
sparkle/CLI/construct_portfolio_selector.py
sparkle/CLI/generate_report.py
sparkle/CLI/initialise.py
sparkle/CLI/jobs.py
sparkle/CLI/load_snapshot.py
sparkle/CLI/remove_feature_extractor.py
sparkle/CLI/remove_instances.py
sparkle/CLI/remove_solver.py
sparkle/CLI/run_ablation.py
sparkle/CLI/run_parallel_portfolio.py
sparkle/CLI/run_portfolio_selector.py
sparkle/CLI/run_solvers.py
sparkle/CLI/save_snapshot.py
sparkle/CLI/status.py
sparkle/CLI/core/__init__.py
sparkle/CLI/core/compute_features.py
sparkle/CLI/core/run_portfolio_selector_core.py
sparkle/CLI/help/__init__.py
sparkle/CLI/help/argparse_custom.py
sparkle/CLI/help/global_variables.py
sparkle/CLI/help/jobs.py
sparkle/CLI/help/logging.py
sparkle/CLI/help/nicknames.py
sparkle/CLI/help/reporting_scenario.py
sparkle/CLI/help/snapshot_help.py
sparkle/CLI/help/system_status.py
sparkle/Components/description_epstopdf.txt
sparkle/Components/paramils2.3.8-source.tgz
sparkle/Components/sparkle_settings.ini
sparkle/Components/Sparkle-SAT-verifier/Makefile
sparkle/Components/Sparkle-SAT-verifier/README
sparkle/Components/Sparkle-SAT-verifier/SAT
sparkle/Components/Sparkle-SAT-verifier/SAT.cc
sparkle/Components/Sparkle-latex-source/SparkleReport.bib
sparkle/Components/Sparkle-latex-source/template-Sparkle-for-configuration.tex
sparkle/Components/Sparkle-latex-source/template-Sparkle-for-parallel-portfolio.tex
sparkle/Components/Sparkle-latex-source/template-Sparkle-for-selection.tex
sparkle/Components/ablationAnalysis-0.9.4/LICENSE.txt
sparkle/Components/ablationAnalysis-0.9.4/README.txt
sparkle/Components/ablationAnalysis-0.9.4/ablationAnalysis
sparkleai-0.9.3.2.dist-info/licenses/LICENCE.txt
sparkleai-0.9.3.2.dist-info/METADATA
sparkleai-0.9.3.2.dist-info/WHEEL
sparkleai-0.9.3.2.dist-info/entry_points.txt
sparkleai-0.9.3.2.dist-info/top_level.txt
sparkleai-0.9.3.2.dist-info/RECORD
